pymeshb.so
pymeshb-0.0.6.dist-info/METADATA
pymeshb-0.0.6.dist-info/RECORD
pymeshb-0.0.6.dist-info/WHEEL
pymeshb-0.0.6.dist-info/top_level.txt
