Metadata-Version: 2.1
Name: pymeshb
Version: 0.0.6
Summary: LibMeshb Python wrapper to read/write *.mesh[b]/*.sol[b] file.
Home-page: https://github.com/jvanharen/pymeshb
Author: Julien Vanharen
Author-email: julien.vanharen@inria.fr
License: UNKNOWN
Platform: UNKNOWN
Classifier: License :: OSI Approved :: MIT License
Classifier: Operating System :: OS Independent
Classifier: Programming Language :: Python
Classifier: Programming Language :: Python :: 2
Classifier: Programming Language :: Python :: 3
Classifier: Topic :: Scientific/Engineering
Requires-Dist: numpy (>=1.13.3)
